terrajinja/sbp/datadog/monitor_json.py
terrajinja/sbp/datadog/synthetics_test_json.py
terrajinja_sbp_datadog-1.0.1.dist-info/LICENSE
terrajinja_sbp_datadog-1.0.1.dist-info/METADATA
terrajinja_sbp_datadog-1.0.1.dist-info/WHEEL
terrajinja_sbp_datadog-1.0.1.dist-info/top_level.txt
terrajinja_sbp_datadog-1.0.1.dist-info/RECORD
