Metadata-Version: 2.1
Name: terrajinja-sbp-datadog
Version: 1.0.1
Summary: Terrajinja extension for automation using cdktf
Home-page: https://gitlab/terrajinja
Author: Terrajinja Team
Author-email: int-terrajinja@schubergphilis.com
License: MIT
Classifier: Development Status :: 4 - Beta
Classifier: Intended Audience :: Developers
Classifier: License :: OSI Approved :: MIT License
Classifier: Natural Language :: English
Classifier: Programming Language :: Python :: 3.11
License-File: LICENSE
Requires-Dist: cdktf-cdktf-provider-datadog >=11.6.0
Requires-Dist: cdktf >=0.20.3
